LICENSE
README.md
setup.py
threedcellcomposer/ThreeDCellComposer.py
threedcellcomposer/__init__.py
threedcellcomposer/coloring_3D.py
threedcellcomposer/deepcell_only.py
threedcellcomposer/match_2D_cells.py
threedcellcomposer/match_3D_cells.py
threedcellcomposer/match_3D_nuclei.py
threedcellcomposer/meshing_3D.py
threedcellcomposer/preprocessing.py
threedcellcomposer/single_method_eval_3D.py
threedcellcomposer/threedcellcomposer.py
threedcellcomposer.egg-info/PKG-INFO
threedcellcomposer.egg-info/SOURCES.txt
threedcellcomposer.egg-info/dependency_links.txt
threedcellcomposer.egg-info/requires.txt
threedcellcomposer.egg-info/top_level.txt