Metadata-Version: 2.1
Name: threedcellcomposer
Version: 1.5.4
Summary: 3D cell segmentation by composing 2D segmentations
Home-page: https://github.com/murphylab/3DCellComposer/
Author: Haoran Chen and Ted Zhang and Robert F. Murphy
Author-email: murphy@cmu.edu
License: MIT
Classifier: Development Status :: 5 - Production/Stable
Classifier: Intended Audience :: Science/Research
Classifier: License :: OSI Approved :: MIT License
Classifier: Operating System :: POSIX :: Linux
Classifier: Operating System :: MacOS :: MacOS X
Classifier: Programming Language :: Python :: 3
Classifier: Programming Language :: Python :: 3.4
Classifier: Programming Language :: Python :: 3.5
Classifier: Topic :: Scientific/Engineering :: Bio-Informatics
Classifier: Topic :: Scientific/Engineering :: Image Processing
License-File: LICENSE
